CHANGES
INSTALL
MANIFEST.in
README.txt
runner.py
setup.py
omnikey2ivy/__init__.py
omnikey2ivy/omnikey2ivy.py
omnikey2ivy.egg-info/PKG-INFO
omnikey2ivy.egg-info/SOURCES.txt
omnikey2ivy.egg-info/dependency_links.txt
omnikey2ivy.egg-info/requires.txt
omnikey2ivy.egg-info/top_level.txt
omnikey2ivy/RFIDIOt/CHANGES
omnikey2ivy/RFIDIOt/README.TXT
omnikey2ivy/RFIDIOt/RFIDIOt.py
omnikey2ivy/RFIDIOt/RFIDIOtconfig.py
omnikey2ivy/RFIDIOt/__init__.py
omnikey2ivy/RFIDIOt/iso3166.py
omnikey2ivy/RFIDIOt/pynfc.py
scripts/omnikey2ivy