Metadata-Version: 1.0
Name: omnikey2ivy
Version: 0.1.2
Summary: emit card id on Ivy software bus
Home-page: http://pypi.python.org/pypi/omnikey2ivy/
Author: Fabien Andre
Author-email: fabien.andre@enac.fr
License: UNKNOWN
Platform: UNKNOWN
Classifier: Programming Language :: Python
Classifier: Development Status :: 2 - Pre-Alpha
Classifier: Environment :: Console
Classifier: Intended Audience :: Developers
Classifier: License :: OSI Approved :: GNU General Public License (GPL)
Classifier: Operating System :: POSIX :: Linux
